rec/__init__.py
rec/__main__.py
rec/lib/__init__.py
rec/lib/environment.py
rec/lib/launcher.py
runtime_environment_capture-0.2.1.dist-info/METADATA
runtime_environment_capture-0.2.1.dist-info/WHEEL
runtime_environment_capture-0.2.1.dist-info/entry_points.txt
runtime_environment_capture-0.2.1.dist-info/top_level.txt
runtime_environment_capture-0.2.1.dist-info/RECORD
