Metadata-Version: 2.1
Name: runtime-environment-capture
Version: 0.2.1
Summary: A wrapper to collect data for ensuring reproducibility.
Home-page: https://github.com/carsonwoods/rec
Author: Carson Woods
License: MIT
Platform: UNKNOWN
Classifier: License :: OSI Approved :: MIT License
Classifier: Programming Language :: Python :: 3
Classifier: Intended Audience :: Developers
Classifier: Intended Audience :: Information Technology
Classifier: Intended Audience :: Science/Research
Classifier: Operating System :: MacOS
Classifier: Operating System :: POSIX :: Linux
Classifier: Operating System :: Unix
Requires-Python: >=3.6
